coca_utility/__init__.py
coca_utility/debug.py
coca_utility/financial_processing.py
coca_utility/line.py
coca_utility/timeseries_analysis.py
coca_utility/websocket.py
coca_utility-0.1.9.dist-info/LICENSE
coca_utility-0.1.9.dist-info/METADATA
coca_utility-0.1.9.dist-info/WHEEL
coca_utility-0.1.9.dist-info/RECORD
