Metadata-Version: 2.1
Name: coca-utility
Version: 0.1.9
Summary: 
Home-page: https://github.com/CocaButon60s/coca_utility
License: MIT
Author: Hiroyuki Ikuno
Author-email: sam2kaikaramegusuri@gmail.com
Requires-Python: >=3.11,<4.0
Classifier: License :: OSI Approved :: MIT License
Classifier: Programming Language :: Python :: 3
Classifier: Programming Language :: Python :: 3.11
Requires-Dist: joblib (>=1.3.2,<2.0.0)
Requires-Dist: requests (>=2.31.0,<3.0.0)
Requires-Dist: statsmodels (>=0.14.0,<0.15.0)
Requires-Dist: websockets (>=11.0.3,<12.0.0)
